Workbook

Sheet Read Me
A1: Instructions
A2: BS_Raw is where you paste line items exactly as they appear in the company’s filing.
A3: Category column must match the Balance Sheet category master list exactly, no edits.
A4: BS_Final aggregates values by category automatically.
A5: All numbers are point-in-time (e.g., as of Dec 31).
A6: Ensure BEGIN = prior year’s ending balance and END = current year’s balance — this is crucial for rollforwards.
A7: Units (millions/thousands) must match the filing. Note clearly at the top.

Sheet Glossary
A1: Glossary
A2: Term | B2: Meaning
A3: BEGIN | B3: Balance at the start of the fiscal period.
A4: END | B4: Balance at the end of the fiscal period.
A5: Assets – Current | B5: Cash, receivables, inventory — expected to be used or converted within 1 year.
A6: Assets – Noncurrent | B6: PP&E, intangibles — held for more than 1 year.
A7: Liabilities – Current | B7: Obligations due within 1 year.
A8: Liabilities – Noncurrent | B8: Obligations due after 1 year.
A9: Equity | B9: Ownership interest in the company (retained earnings, common stock).
A10: PP&E | B10: Property, Plant & Equipment, net of depreciation.
A11: Retained Earnings | B11: Cumulative net income not distributed as dividends.
A12: Other Current / Noncurrent Assets/Liabilities | B12: Balancing categories for line items that don’t fit neatly into main classifications.
A16: Legend
A17: Term | B17: Meaning
A18: Cash & Cash Equivalents | B18: The company’s most liquid assets — cash on hand and short-term investments easily converted to cash (e.g., money market funds).
A19: Accounts Receivable | B19: Amounts customers owe for goods or services already delivered but not yet paid for.
A20: Inventory | B20: Goods or materials held for sale or use in production (often zero for software companies like GitLab).
A21: Other Current Assets | B21: Short-term assets expected to convert to cash within a year, such as prepaid expenses or deferred contract costs.
A22: PP&E, net | B22: Property, plant, and equipment minus accumulated depreciation — represents tangible long-term assets used in operations.
A23: Intangible Assets | B23: Non-physical long-term assets like patents, software, trademarks, or acquired technology; excludes goodwill unless stated.
A24: Other Noncurrent Assets | B24: Long-term items not classified elsewhere, such as deposits, right-of-use assets, or long-term deferred costs.
A25: Accounts Payable | B25: Amounts owed to suppliers or vendors for goods/services received but not yet paid for.
A26: Short-Term Debt | B26: Borrowings or loan obligations due within 12 months (GitLab currently has none).
A27: Other Current Liabilities | B27: Miscellaneous short-term obligations like accrued expenses, payroll, or taxes payable.
A28: Long-Term Debt | B28: Borrowings or loan obligations due in more than one year (GitLab currently has none).
... A36: Ignore | B36: Used for subtotals or disclosure-only lines that shouldn’t be mapped directly into modeling categories (e.g., “Total Assets”).

Sheet BS_Raw
A1: GitLab Inc. Consolidated Balance Sheets ($ in thousands, except per share data)
A2: Raw Label | B2: January 31, 2025 (1) | C2: January 31, 2024 (1) | D2: Year 3 (NULL)* | E2: Category | F2: Notes
A3: ASSETS | E3: Ignore | F3: Title
A4: CURRENT ASSETS: | E4: Ignore | F4: Title
A5: Cash and cash equivalents | B5: 227649 | C5: 287996 | E5: Cash & Cash Equivalents | F5: Core liquid asset for daily operations.
A6: Short-term investments | B6: 764728 | C6: 748289 | E6: Other Current Assets | F6: Marketable securities; near-cash and easily convertible.
A7: Accounts receivable, net of allowance for doubtful accounts of $991 and $673 as of January 31, 2025 and January 31, 2024, respectively | B7: 264565 | C7: 166731 | E7: Accounts Receivable | F7: Trade receivables due from customers.
A8: Deferred contract acquisition costs, current | B8: 38964 | C8: 32300 | E8: Other Current Assets | F8: Current prepaid customer acquisition costs amortized within 12 months.
A9: Prepaid expenses and other current assets | B9: 40411 | C9: 49143 | E9: Other Current Assets | F9: Miscellaneous current assets such as prepaid services or insurance.
A10: Total current assets | B10: 1336317 | C10: 1284459 | E10: Ignore | F10: Subtotal only.
A11: Property and equipment, net | B11: 4013 | C11: 2954 | E11: PP&E, net | F11: Tangible fixed assets used in operations.
A12: Operating lease right-of-use assets | B12: 381 | C12: 405 | E12: Other Noncurrent Assets | F12: Long-term lease assets recognized under ASC 842.
A13: Goodwill | B13: 16139 | C13: 8145 | E13: Intangible Assets | F13: Acquisition premium; indefinite-lived intangible.
A14: Intangible assets, net | B14: 17834 | C14: 1733 | E14: Intangible Assets | F14: Finite-lived acquired intangibles (e.g., technology).
A15: Deferred contract acquisition costs, non-current | B15: 20142 | C15: 19317 | E15: Other Noncurrent Assets | F15: Long-term deferred acquisition costs amortized beyond one year.
A16: Other non-current assets | B16: 4437 | C16: 4390 | E16: Other Noncurrent Assets | F16: Miscellaneous long-term assets not classified elsewhere.
A17: TOTAL ASSETS | B17: 1399263 | C17: 1321403 | E17: Ignore | F17: Subtotal.
A18: LIABILITIES AND STOCKHOLDERS' EQUITY | E18: Ignore | F18: Title
A19: CURRENT LIABILITIES: | E19: Ignore | F19: Title
A20: Accounts payable | B20: 7519 | C20: 1738 | E20: Accounts Payable | F20: Trade payables to vendors and suppliers.
A21: Accrued expenses and other current liabilities | B21: 54680 | C21: 301262 | E21: Other Current Liabilities | F21: Accrued short-term obligations (non-payroll).
A22: Accrued compensation and benefits | B22: 40233 | C22: 35809 | E22: Other Current Liabilities | F22: Payroll-related accruals due within a year.
A23: Deferred revenue, current | B23: 442599 | C23: 338348 | E23: Deferred Revenue | F23: Customer prepayments to be recognized within 12 months.
A24: Total current liabilities | B24: 545031 | C24: 677157 | E24: Ignore | F24: Subtotal.
A25: Deferred revenue, non-current | B25: 26369 | C25: 23794 | E25: Deferred Revenue | F25: Long-term portion of deferred revenue; combine with current for total.
A26: Other non-current liabilities | B26: 6557 | C26: 14060 | E26: Other Noncurrent Liabilities | F26: Long-term obligations such as lease or deferred tax liabilities.
A27: TOTAL LIABILITIES | B27: 577957 | C27: 715011 | E27: Ignore | F27: Subtotal.
A28: Commitments and contingencies (Note 14) | E28: Ignore | F28: Disclosure item, not a balance-sheet account.
A29: STOCKHOLDERS' EQUITY | E29: Ignore | F29: Title
A30: Preferred stock, $0.0000025 par value; 50,000 shares authorized as of January 31, 2025 and January 31, 2024; no shares issued and outstanding as of January 31, 2025 and January 31, 2024 | B30: - | C30: - | E30: Other Equity | F30: Authorized but unissued; informational only.
A31: Class A Common stock, $0.0000025 par value; 1,500,000 shares authorized as of January 31, 2025 and January 31, 2024; 144,444 and 114,670 shares issued and outstanding as of January 31, 2025 and January 31, 2024, respectively | B31: - | C31: - | E31: Common Stock / APIC | F31: Combined with APIC for modeling simplicity.
A32: Class B Common stock; $0.0000025 par value; 250,000 shares authorized as of January 31, 2025 and January 31, 2024; 19,469 and 42,887 shares issued and outstanding as of January 31, 2025 and January 31, 2024, respectively | B32: - | C32: - | E32: Common Stock / APIC | F32: Same as above; par value immaterial.
A33: Additional paid-in capital | B33: 1952031 | C33: 1718661 | E33: Common Stock / APIC | F33: Main contributed-capital component.
A34: Accumulated deficit | B34: -1167614 | C34: -1161288 | E34: Retained Earnings | F34: Represents cumulative net losses (negative retained earnings).
A35: Accumulated other comprehensive income (loss) | B35: -8508 | C35: 2398 | E35: Accumulated OCI | F35: Captures unrealized gains/losses and FX adjustments.
A36: Total GitLab stockholders' equity | B36: 775909 | C36: 559771 | E36: Ignore | F36: Subtotal.
A37: Noncontrolling interests | B37: 45397 | C37: 46621 | E37: Other Equity | F37: Equity held by minority shareholders in subsidiaries.
A38: TOTAL STOCKHOLDERS' EQUITY | B38: 821306 | C38: 606392 | E38: Ignore | F38: Subtotal.
A39: TOTAL LIABILITIES AND STOCKHOLDERS' EQUITY | B39: 1399263 | C39: 1321403 | E39: Ignore | F39: Final subtotal; ensures Assets = Liabilities + Equity.
A42: * Only two years are reported for the balance sheet, because U.S. GAAP only requires companies to present the two most recent fiscal years (unlike income statements, cash flows, and equity statements where three years are required.) GitLab is standard and fully compliant with two years here.

Sheet BS_Final
A1: GitLab Inc. Consolidated Balance Sheets ($ in thousands, except per share data)
A2: Category | B2: January 31, 2025 (1) | C2: January 31, 2024 (1) | D2: NULL | G2: Total Assets 2025 | H2: Total Assets 2024 | I2: Total Assets 2023 | J2: Total Liabilities 2025 | K2: Total Liabilities 2024 | L2: Total Liabilities 2023 | M2: Shareholders' Equity 2025 | N2: Shareholders' Equity 2024 | O2: Shareholders' Equity 2023
A3: Cash & Cash Equivalents | B3: =SUMIF(BS_Raw!$E:$E,$A3,BS_Raw!$B:$B) -> 227649 | C3: =SUMIF(BS_Raw!$E:$E,$A3,BS_Raw!$C:$C) -> 287996 | D3: =SUMIF(BS_Raw!$E:$E,$A3,BS_Raw!$D:$D) -> 0 | G3: =B3+B4+B5+B6+B7+B8+B9 -> 1399263 | H3: =SUM(C3:C9) -> 1321403 | I3: =SUM(D3:D9) -> 0 | J3: =B10+B11+B12+B13+B14 -> 577957 | K3: =SUM(C10:C15) -> 2433672 | L3: =SUM(D10:D14) -> 0 | M3: =B15+B16+B17+B18 -> 821306 | N3: =SUM(C15:C18) -> 606392 | O3: =SUM(D15:D18) -> 0
A4: Accounts Receivable | B4: =SUMIF(BS_Raw!$E:$E,$A4,BS_Raw!$B:$B) -> 264565 | C4: =SUMIF(BS_Raw!$E:$E,$A4,BS_Raw!$C:$C) -> 166731 | D4: =SUMIF(BS_Raw!$E:$E,$A4,BS_Raw!$D:$D) -> 0
A5: Inventory | B5: =SUMIF(BS_Raw!$E:$E,$A5,BS_Raw!$B:$B) -> 0 | C5: =SUMIF(BS_Raw!$E:$E,$A5,BS_Raw!$C:$C) -> 0 | D5: =SUMIF(BS_Raw!$E:$E,$A5,BS_Raw!$D:$D) -> 0
A6: PP&E, net | B6: =SUMIF(BS_Raw!$E:$E,$A6,BS_Raw!$B:$B) -> 4013 | C6: =SUMIF(BS_Raw!$E:$E,$A6,BS_Raw!$C:$C) -> 2954 | D6: =SUMIF(BS_Raw!$E:$E,$A6,BS_Raw!$D:$D) -> 0
A7: Other Current Assets | B7: =SUMIF(BS_Raw!$E:$E,$A7,BS_Raw!$B:$B) -> 844103 | C7: =SUMIF(BS_Raw!$E:$E,$A7,BS_Raw!$C:$C) -> 829732 | D7: =SUMIF(BS_Raw!$E:$E,$A7,BS_Raw!$D:$D) -> 0
A8: Intangible Assets | B8: =SUMIF(BS_Raw!$E:$E,$A8,BS_Raw!$B:$B) -> 33973 | C8: =SUMIF(BS_Raw!$E:$E,$A8,BS_Raw!$C:$C) -> 9878 | D8: =SUMIF(BS_Raw!$E:$E,$A8,BS_Raw!$D:$D) -> 0
A9: Other Noncurrent Assets | B9: =SUMIF(BS_Raw!$E:$E,$A9,BS_Raw!$B:$B) -> 24960 | C9: =SUMIF(BS_Raw!$E:$E,$A9,BS_Raw!$C:$C) -> 24112 | D9: =SUMIF(BS_Raw!$E:$E,$A9,BS_Raw!$D:$D) -> 0
A10: Accounts Payable | B10: =SUMIF(BS_Raw!$E:$E,$A10,BS_Raw!$B:$B) -> 7519 | C10: =SUMIF(BS_Raw!$E:$E,$A10,BS_Raw!$C:$C) -> 1738 | D10: =SUMIF(BS_Raw!$E:$E,$A10,BS_Raw!$D:$D) -> 0
A11: Deferred Revenue | B11: =SUMIF(BS_Raw!$E:$E,$A11,BS_Raw!$B:$B) -> 468968 | C11: =SUMIF(BS_Raw!$E:$E,$A11,BS_Raw!$C:$C) -> 362142 | D11: =SUMIF(BS_Raw!$E:$E,$A11,BS_Raw!$D:$D) -> 0
A12: Other Current Liabilities | B12: =SUMIF(BS_Raw!$E:$E,$A12,BS_Raw!$B:$B) -> 94913 | C12: =SUMIF(BS_Raw!$E:$E,$A12,BS_Raw!$C:$C) -> 337071 | D12: =SUMIF(BS_Raw!$E:$E,$A12,BS_Raw!$D:$D) -> 0
A13: Long-Term Debt | B13: =SUMIF(BS_Raw!$E:$E,$A13,BS_Raw!$B:$B) -> 0 | C13: =SUMIF(BS_Raw!$E:$E,$A13,BS_Raw!$C:$C) -> 0 | D13: =SUMIF(BS_Raw!$E:$E,$A13,BS_Raw!$D:$D) -> 0
A14: Other Noncurrent Liabilities | B14: =SUMIF(BS_Raw!$E:$E,$A14,BS_Raw!$B:$B) -> 6557 | C14: =SUMIF(BS_Raw!$E:$E,$A14,BS_Raw!$C:$C) -> 14060 | D14: =SUMIF(BS_Raw!$E:$E,$A14,BS_Raw!$D:$D) -> 0
A15: Common Stock / APIC | B15: =SUMIF(BS_Raw!$E:$E,$A15,BS_Raw!$B:$B) -> 1952031 | C15: =SUMIF(BS_Raw!$E:$E,$A15,BS_Raw!$C:$C) -> 1718661 | D15: =SUMIF(BS_Raw!$E:$E,$A15,BS_Raw!$D:$D) -> 0
... A18: Accumulated OCI | B18: =SUMIF(BS_Raw!$E:$E,$A18,BS_Raw!$B:$B) -> -8508 | C18: =SUMIF(BS_Raw!$E:$E,$A18,BS_Raw!$C:$C) -> 2398 | D18: =SUMIF(BS_Raw!$E:$E,$A18,BS_Raw!$D:$D) -> 0
A22: Fixes made to template to make it balance (Assets - (Liabilities + Equity))
A23: - Add an Other Current Assets line = 79,375 (Deferred contract acquisition costs, current 38,964 + Prepaid expenses & other current assets 40,411)
A24: - Combine Common Stock / APIC and Additional Paid-In Capital
A25: - Add Accumulated OCI
A26: - No balance check was included on the original template, numbers were checked both manually and through GPT. Balance check column may be added to final deliverables at the end of the project.
